bittty/__init__.py
bittty/buffer.py
bittty/charsets.py
bittty/color.py
bittty/constants.py
bittty/style.py
bittty/tcaps.py
bittty/terminal.py
bittty/parser/__init__.py
bittty/parser/core.py
bittty/parser/csi.py
bittty/parser/dcs.py
bittty/parser/escape.py
bittty/parser/osc.py
bittty/pty/__init__.py
bittty/pty/base.py
bittty/pty/unix.py
bittty/pty/windows.py
bittty-0.0.10.dist-info/licenses/LICENSE.md
bittty-0.0.10.dist-info/WHEEL
bittty-0.0.10.dist-info/METADATA
bittty-0.0.10.dist-info/RECORD
