Metadata-Version: 2.4
Name: bittty
Version: 0.0.10
Summary: a pure python tty
Author-email: Gareth Davidson <gaz@bitplane.net>
Requires-Python: >=3.10
License-File: LICENSE.md
Requires-Dist: pywinpty==2.0.15; sys_platform == 'win32'
Requires-Dist: pre-commit ; extra == "dev"
Requires-Dist: pytest ; extra == "dev"
Requires-Dist: coverage ; extra == "dev"
Requires-Dist: pytest-cov ; extra == "dev"
Requires-Dist: pytest-asyncio ; extra == "dev"
Requires-Dist: plotext ; extra == "dev"
Requires-Dist: build ; extra == "dev"
Requires-Dist: twine ; extra == "dev"
Requires-Dist: ruff ; extra == "dev"
Requires-Dist: pydoc-markdown ; extra == "dev"
Requires-Dist: snakeviz ; extra == "dev"
Provides-Extra: dev
